[
  {
    "jim_schema_export": "{\"face_templates\" : [{\"passport_no\":\"A12345\",\"template_vector\":[0.112, -0.442, 0.223, 0.901, -0.114, 0.552],\"algo_version\":\"v1\",\"created_at\":\"2025-03-12T10:15:30+08:00\"}, \n {\"passport_no\":\"P10002\",\"template_vector\":[0.12, -0.22, 0.32, 0.42, -0.52],\"algo_version\":\"v1\",\"created_at\":\"2025-03-12T09:02:00+08:00\"}, \n {\"passport_no\":\"P10003\",\"template_vector\":[0.13, -0.23, 0.33, 0.43, -0.53],\"algo_version\":\"v1\",\"created_at\":\"2025-03-12T09:03:00+08:00\"}, \n {\"passport_no\":\"P10004\",\"template_vector\":[0.14, -0.24, 0.34, 0.44, -0.54],\"algo_version\":\"v1\",\"created_at\":\"2025-03-12T09:04:00+08:00\"}, \n {\"passport_no\":\"P10005\",\"template_vector\":[0.15, -0.25, 0.35, 0.45, -0.55],\"algo_version\":\"v1\",\"created_at\":\"2025-03-12T09:05:00+08:00\"}, \n {\"passport_no\":\"P10006\",\"template_vector\":[0.16, -0.26, 0.36, 0.46, -0.56],\"algo_version\":\"v1\",\"created_at\":\"2025-03-12T09:06:00+08:00\"}, \n {\"passport_no\":\"P10007\",\"template_vector\":[0.17, -0.27, 0.37, 0.47, -0.57],\"algo_version\":\"v1\",\"created_at\":\"2025-03-12T09:07:00+08:00\"}, \n {\"passport_no\":\"P10008\",\"template_vector\":[0.18, -0.28, 0.38, 0.48, -0.58],\"algo_version\":\"v1\",\"created_at\":\"2025-03-12T09:08:00+08:00\"}, \n {\"passport_no\":\"P10009\",\"template_vector\":[0.19, -0.29, 0.39, 0.49, -0.59],\"algo_version\":\"v1\",\"created_at\":\"2025-03-12T09:09:00+08:00\"}, \n {\"passport_no\":\"P10010\",\"template_vector\":[0.20, -0.30, 0.40, 0.50, -0.60],\"algo_version\":\"v1\",\"created_at\":\"2025-03-12T09:10:00+08:00\"}, \n {\"passport_no\":\"P10011\",\"template_vector\":[0.21, -0.31, 0.41, 0.51, -0.61],\"algo_version\":\"v1\",\"created_at\":\"2025-03-12T09:11:00+08:00\"}, \n {\"passport_no\":\"P10012\",\"template_vector\":[0.22, -0.32, 0.42, 0.52, -0.62],\"algo_version\":\"v1\",\"created_at\":\"2025-03-12T09:12:00+08:00\"}, \n {\"passport_no\":\"P10013\",\"template_vector\":[0.23, -0.33, 0.43, 0.53, -0.63],\"algo_version\":\"v1\",\"created_at\":\"2025-03-12T09:13:00+08:00\"}, \n {\"passport_no\":\"P10014\",\"template_vector\":[0.24, -0.34, 0.44, 0.54, -0.64],\"algo_version\":\"v1\",\"created_at\":\"2025-03-12T09:14:00+08:00\"}, \n {\"passport_no\":\"P10015\",\"template_vector\":[0.25, -0.35, 0.45, 0.55, -0.65],\"algo_version\":\"v1\",\"created_at\":\"2025-03-12T09:15:00+08:00\"}, \n {\"passport_no\":\"P10016\",\"template_vector\":[0.26, -0.36, 0.46, 0.56, -0.66],\"algo_version\":\"v1\",\"created_at\":\"2025-03-12T09:16:00+08:00\"}, \n {\"passport_no\":\"P10017\",\"template_vector\":[0.27, -0.37, 0.47, 0.57, -0.67],\"algo_version\":\"v1\",\"created_at\":\"2025-03-12T09:17:00+08:00\"}, \n {\"passport_no\":\"P10018\",\"template_vector\":[0.28, -0.38, 0.48, 0.58, -0.68],\"algo_version\":\"v1\",\"created_at\":\"2025-03-12T09:18:00+08:00\"}, \n {\"passport_no\":\"P10019\",\"template_vector\":[0.29, -0.39, 0.49, 0.59, -0.69],\"algo_version\":\"v1\",\"created_at\":\"2025-03-12T09:19:00+08:00\"}, \n {\"passport_no\":\"P10020\",\"template_vector\":[0.30, -0.40, 0.50, 0.60, -0.70],\"algo_version\":\"v1\",\"created_at\":\"2025-03-12T09:20:00+08:00\"}, \n {\"passport_no\":\"P10021\",\"template_vector\":[0.31, -0.41, 0.51, 0.61, -0.71],\"algo_version\":\"v1\",\"created_at\":\"2025-03-12T09:21:00+08:00\"}, \n {\"passport_no\":\"P10022\",\"template_vector\":[0.32, -0.42, 0.52, 0.62, -0.72],\"algo_version\":\"v1\",\"created_at\":\"2025-03-12T09:22:00+08:00\"}, \n {\"passport_no\":\"P10023\",\"template_vector\":[0.33, -0.43, 0.53, 0.63, -0.73],\"algo_version\":\"v1\",\"created_at\":\"2025-03-12T09:23:00+08:00\"}, \n {\"passport_no\":\"P10024\",\"template_vector\":[0.34, -0.44, 0.54, 0.64, -0.74],\"algo_version\":\"v1\",\"created_at\":\"2025-03-12T09:24:00+08:00\"}, \n {\"passport_no\":\"P10025\",\"template_vector\":[0.35, -0.45, 0.55, 0.65, -0.75],\"algo_version\":\"v1\",\"created_at\":\"2025-03-12T09:25:00+08:00\"}, \n {\"passport_no\":\"P10026\",\"template_vector\":[0.36, -0.46, 0.56, 0.66, -0.76],\"algo_version\":\"v1\",\"created_at\":\"2025-03-12T09:26:00+08:00\"}, \n {\"passport_no\":\"P10027\",\"template_vector\":[0.37, -0.47, 0.57, 0.67, -0.77],\"algo_version\":\"v1\",\"created_at\":\"2025-03-12T09:27:00+08:00\"}, \n {\"passport_no\":\"P10028\",\"template_vector\":[0.38, -0.48, 0.58, 0.68, -0.78],\"algo_version\":\"v1\",\"created_at\":\"2025-03-12T09:28:00+08:00\"}, \n {\"passport_no\":\"P10029\",\"template_vector\":[0.39, -0.49, 0.59, 0.69, -0.79],\"algo_version\":\"v1\",\"created_at\":\"2025-03-12T09:29:00+08:00\"}, \n {\"passport_no\":\"P10030\",\"template_vector\":[0.40, -0.50, 0.60, 0.70, -0.80],\"algo_version\":\"v1\",\"created_at\":\"2025-03-12T09:30:00+08:00\"}], \"jim_nonresidents\" : [{\"passport_no\":\"A12345\",\"fname\":\"Chee Keong\",\"lname\":\"Myat\",\"date_of_birth\":\"1998-10-22\",\"exp_date\":\"2030-02-10\",\"nationality\":\"Myanmar\",\"issue_date\":\"2025-02-10\",\"issue_office\":\"Yangon\",\"passport_photo\":\"\\\\xffd8ffe000104a464946\",\"visa_type\":\"Student\",\"photo_pattern\":\"DEF123\"}, \n {\"passport_no\":\"P10002\",\"fname\":\"Nguyen\",\"lname\":\"An\",\"date_of_birth\":\"1999-02-14\",\"exp_date\":\"2030-02-14\",\"nationality\":\"Vietnam\",\"issue_date\":\"2025-02-14\",\"issue_office\":\"Hanoi\",\"passport_photo\":\"\\\\xffd8ffe000104a464946\",\"visa_type\":\"Student\",\"photo_pattern\":\"PATJ002\"}, \n {\"passport_no\":\"P10003\",\"fname\":\"Arjun\",\"lname\":\"Singh\",\"date_of_birth\":\"1997-05-21\",\"exp_date\":\"2031-05-21\",\"nationality\":\"India\",\"issue_date\":\"2024-05-21\",\"issue_office\":\"New Delhi\",\"passport_photo\":\"\\\\xffd8ffe000104a464946\",\"visa_type\":\"Worker\",\"photo_pattern\":\"PATJ003\"}, \n {\"passport_no\":\"P10004\",\"fname\":\"Sokha\",\"lname\":\"Chea\",\"date_of_birth\":\"2000-08-09\",\"exp_date\":\"2032-08-09\",\"nationality\":\"Cambodia\",\"issue_date\":\"2025-08-09\",\"issue_office\":\"Phnom Penh\",\"passport_photo\":\"\\\\xffd8ffe000104a464946\",\"visa_type\":\"Student\",\"photo_pattern\":\"PATJ004\"}, \n {\"passport_no\":\"P10005\",\"fname\":\"Li\",\"lname\":\"Xuan\",\"date_of_birth\":\"1998-11-17\",\"exp_date\":\"2031-11-17\",\"nationality\":\"China\",\"issue_date\":\"2024-11-17\",\"issue_office\":\"Beijing\",\"passport_photo\":\"\\\\xffd8ffe000104a464946\",\"visa_type\":\"Worker\",\"photo_pattern\":\"PATJ005\"}, \n {\"passport_no\":\"P10006\",\"fname\":\"Aung\",\"lname\":\"Min\",\"date_of_birth\":\"1996-03-03\",\"exp_date\":\"2030-03-03\",\"nationality\":\"Myanmar\",\"issue_date\":\"2025-03-03\",\"issue_office\":\"Yangon\",\"passport_photo\":\"\\\\xffd8ffe000104a464946\",\"visa_type\":\"Student\",\"photo_pattern\":\"PATJ006\"}, \n {\"passport_no\":\"P10007\",\"fname\":\"Maria\",\"lname\":\"Santos\",\"date_of_birth\":\"1995-06-12\",\"exp_date\":\"2030-06-12\",\"nationality\":\"Philippines\",\"issue_date\":\"2025-06-12\",\"issue_office\":\"Manila\",\"passport_photo\":\"\\\\xffd8ffe000104a464946\",\"visa_type\":\"Worker\",\"photo_pattern\":\"PATJ007\"}, \n {\"passport_no\":\"P10008\",\"fname\":\"Budi\",\"lname\":\"Hartono\",\"date_of_birth\":\"1994-09-25\",\"exp_date\":\"2029-09-25\",\"nationality\":\"Indonesia\",\"issue_date\":\"2024-09-25\",\"issue_office\":\"Jakarta\",\"passport_photo\":\"\\\\xffd8ffe000104a464946\",\"visa_type\":\"Worker\",\"photo_pattern\":\"PATJ008\"}, \n {\"passport_no\":\"P10009\",\"fname\":\"Sok\",\"lname\":\"Chan\",\"date_of_birth\":\"2001-01-30\",\"exp_date\":\"2033-01-30\",\"nationality\":\"Cambodia\",\"issue_date\":\"2025-01-30\",\"issue_office\":\"Phnom Penh\",\"passport_photo\":\"\\\\xffd8ffe000104a464946\",\"visa_type\":\"Student\",\"photo_pattern\":\"PATJ009\"}, \n {\"passport_no\":\"P10010\",\"fname\":\"Than\",\"lname\":\"Zaw\",\"date_of_birth\":\"1993-04-18\",\"exp_date\":\"2029-04-18\",\"nationality\":\"Myanmar\",\"issue_date\":\"2024-04-18\",\"issue_office\":\"Yangon\",\"passport_photo\":\"\\\\xffd8ffe000104a464946\",\"visa_type\":\"Worker\",\"photo_pattern\":\"PATJ010\"}, \n {\"passport_no\":\"P10011\",\"fname\":\"Emily\",\"lname\":\"Lim\",\"date_of_birth\":\"2002-07-07\",\"exp_date\":\"2034-07-07\",\"nationality\":\"Singapore\",\"issue_date\":\"2025-07-07\",\"issue_office\":\"Singapore\",\"passport_photo\":\"\\\\xffd8ffe000104a464946\",\"visa_type\":\"Student\",\"photo_pattern\":\"PATJ011\"}, \n {\"passport_no\":\"P10012\",\"fname\":\"Rahul\",\"lname\":\"Sharma\",\"date_of_birth\":\"1992-02-02\",\"exp_date\":\"2029-02-02\",\"nationality\":\"India\",\"issue_date\":\"2024-02-02\",\"issue_office\":\"Delhi\",\"passport_photo\":\"\\\\xffd8ffe000104a464946\",\"visa_type\":\"Worker\",\"photo_pattern\":\"PATJ012\"}, \n {\"passport_no\":\"P10013\",\"fname\":\"Chen\",\"lname\":\"Wei\",\"date_of_birth\":\"1993-03-03\",\"exp_date\":\"2030-03-03\",\"nationality\":\"China\",\"issue_date\":\"2025-03-03\",\"issue_office\":\"Shanghai\",\"passport_photo\":\"\\\\xffd8ffe000104a464946\",\"visa_type\":\"Student\",\"photo_pattern\":\"PATJ013\"}, \n {\"passport_no\":\"P10014\",\"fname\":\"Minh\",\"lname\":\"Tran\",\"date_of_birth\":\"1994-04-04\",\"exp_date\":\"2031-04-04\",\"nationality\":\"Vietnam\",\"issue_date\":\"2024-04-04\",\"issue_office\":\"Ho Chi Minh\",\"passport_photo\":\"\\\\xffd8ffe000104a464946\",\"visa_type\":\"Worker\",\"photo_pattern\":\"PATJ014\"}, \n {\"passport_no\":\"P10015\",\"fname\":\"Siti\",\"lname\":\"Aminah\",\"date_of_birth\":\"1995-05-05\",\"exp_date\":\"2032-05-05\",\"nationality\":\"Indonesia\",\"issue_date\":\"2025-05-05\",\"issue_office\":\"Jakarta\",\"passport_photo\":\"\\\\xffd8ffe000104a464946\",\"visa_type\":\"Student\",\"photo_pattern\":\"PATJ015\"}, \n {\"passport_no\":\"P10016\",\"fname\":\"Carlos\",\"lname\":\"Reyes\",\"date_of_birth\":\"1996-06-06\",\"exp_date\":\"2030-06-06\",\"nationality\":\"Philippines\",\"issue_date\":\"2025-06-06\",\"issue_office\":\"Manila\",\"passport_photo\":\"\\\\xffd8ffe000104a464946\",\"visa_type\":\"Worker\",\"photo_pattern\":\"PATJ016\"}, \n {\"passport_no\":\"P10017\",\"fname\":\"Sok\",\"lname\":\"Dara\",\"date_of_birth\":\"1997-07-07\",\"exp_date\":\"2031-07-07\",\"nationality\":\"Cambodia\",\"issue_date\":\"2024-07-07\",\"issue_office\":\"Phnom Penh\",\"passport_photo\":\"\\\\xffd8ffe000104a464946\",\"visa_type\":\"Student\",\"photo_pattern\":\"PATJ017\"}, \n {\"passport_no\":\"P10018\",\"fname\":\"Zaw\",\"lname\":\"Tun\",\"date_of_birth\":\"1998-08-08\",\"exp_date\":\"2032-08-08\",\"nationality\":\"Myanmar\",\"issue_date\":\"2025-08-08\",\"issue_office\":\"Yangon\",\"passport_photo\":\"\\\\xffd8ffe000104a464946\",\"visa_type\":\"Worker\",\"photo_pattern\":\"PATJ018\"}, \n {\"passport_no\":\"P10019\",\"fname\":\"Ng\",\"lname\":\"Kai\",\"date_of_birth\":\"1999-09-09\",\"exp_date\":\"2033-09-09\",\"nationality\":\"Singapore\",\"issue_date\":\"2025-09-09\",\"issue_office\":\"Singapore\",\"passport_photo\":\"\\\\xffd8ffe000104a464946\",\"visa_type\":\"Student\",\"photo_pattern\":\"PATJ019\"}, \n {\"passport_no\":\"P10020\",\"fname\":\"Budi\",\"lname\":\"Santoso\",\"date_of_birth\":\"2000-10-10\",\"exp_date\":\"2034-10-10\",\"nationality\":\"Indonesia\",\"issue_date\":\"2025-10-10\",\"issue_office\":\"Jakarta\",\"passport_photo\":\"\\\\xffd8ffe000104a464946\",\"visa_type\":\"Worker\",\"photo_pattern\":\"PATJ020\"}, \n {\"passport_no\":\"P10021\",\"fname\":\"Maria\",\"lname\":\"Lopez\",\"date_of_birth\":\"2001-11-11\",\"exp_date\":\"2035-11-11\",\"nationality\":\"Philippines\",\"issue_date\":\"2025-11-11\",\"issue_office\":\"Manila\",\"passport_photo\":\"\\\\xffd8ffe000104a464946\",\"visa_type\":\"Student\",\"photo_pattern\":\"PATJ021\"}, \n {\"passport_no\":\"P10022\",\"fname\":\"Aisha\",\"lname\":\"Khan\",\"date_of_birth\":\"2002-12-12\",\"exp_date\":\"2035-12-12\",\"nationality\":\"Pakistan\",\"issue_date\":\"2025-12-12\",\"issue_office\":\"Karachi\",\"passport_photo\":\"\\\\xffd8ffe000104a464946\",\"visa_type\":\"Student\",\"photo_pattern\":\"PATJ022\"}, \n {\"passport_no\":\"P10023\",\"fname\":\"Htet\",\"lname\":\"Aung\",\"date_of_birth\":\"1991-01-13\",\"exp_date\":\"2029-01-13\",\"nationality\":\"Myanmar\",\"issue_date\":\"2024-01-13\",\"issue_office\":\"Yangon\",\"passport_photo\":\"\\\\xffd8ffe000104a464946\",\"visa_type\":\"Worker\",\"photo_pattern\":\"PATJ023\"}, \n {\"passport_no\":\"P10024\",\"fname\":\"Liu\",\"lname\":\"Fang\",\"date_of_birth\":\"1990-02-14\",\"exp_date\":\"2030-02-14\",\"nationality\":\"China\",\"issue_date\":\"2025-02-14\",\"issue_office\":\"Guangzhou\",\"passport_photo\":\"\\\\xffd8ffe000104a464946\",\"visa_type\":\"Worker\",\"photo_pattern\":\"PATJ024\"}, \n {\"passport_no\":\"P10025\",\"fname\":\"Rina\",\"lname\":\"Putri\",\"date_of_birth\":\"2003-03-15\",\"exp_date\":\"2036-03-15\",\"nationality\":\"Indonesia\",\"issue_date\":\"2025-03-15\",\"issue_office\":\"Jakarta\",\"passport_photo\":\"\\\\xffd8ffe000104a464946\",\"visa_type\":\"Student\",\"photo_pattern\":\"PATJ025\"}, \n {\"passport_no\":\"P10026\",\"fname\":\"Sok\",\"lname\":\"Vanna\",\"date_of_birth\":\"1998-04-16\",\"exp_date\":\"2031-04-16\",\"nationality\":\"Cambodia\",\"issue_date\":\"2024-04-16\",\"issue_office\":\"Phnom Penh\",\"passport_photo\":\"\\\\xffd8ffe000104a464946\",\"visa_type\":\"Worker\",\"photo_pattern\":\"PATJ026\"}, \n {\"passport_no\":\"P10027\",\"fname\":\"Andrea\",\"lname\":\"Cruz\",\"date_of_birth\":\"1997-05-17\",\"exp_date\":\"2030-05-17\",\"nationality\":\"Philippines\",\"issue_date\":\"2025-05-17\",\"issue_office\":\"Cebu\",\"passport_photo\":\"\\\\xffd8ffe000104a464946\",\"visa_type\":\"Worker\",\"photo_pattern\":\"PATJ027\"}, \n {\"passport_no\":\"P10028\",\"fname\":\"Tan\",\"lname\":\"Yee\",\"date_of_birth\":\"2004-06-18\",\"exp_date\":\"2037-06-18\",\"nationality\":\"Singapore\",\"issue_date\":\"2025-06-18\",\"issue_office\":\"Singapore\",\"passport_photo\":\"\\\\xffd8ffe000104a464946\",\"visa_type\":\"Student\",\"photo_pattern\":\"PATJ028\"}, \n {\"passport_no\":\"P10029\",\"fname\":\"Prakash\",\"lname\":\"Nair\",\"date_of_birth\":\"1996-07-19\",\"exp_date\":\"2031-07-19\",\"nationality\":\"India\",\"issue_date\":\"2024-07-19\",\"issue_office\":\"Mumbai\",\"passport_photo\":\"\\\\xffd8ffe000104a464946\",\"visa_type\":\"Worker\",\"photo_pattern\":\"PATJ029\"}, \n {\"passport_no\":\"P10030\",\"fname\":\"Mai\",\"lname\":\"Nguyen\",\"date_of_birth\":\"2001-08-20\",\"exp_date\":\"2034-08-20\",\"nationality\":\"Vietnam\",\"issue_date\":\"2025-08-20\",\"issue_office\":\"Da Nang\",\"passport_photo\":\"\\\\xffd8ffe000104a464946\",\"visa_type\":\"Student\",\"photo_pattern\":\"PATJ030\"}]}"
  }
]